adafruit_circuitpython_hashlib-1.4.20.dist-info/licenses/LICENSE
adafruit_hashlib/__init__.py
adafruit_hashlib/_md5.py
adafruit_hashlib/_sha1.py
adafruit_hashlib/_sha224.py
adafruit_hashlib/_sha256.py
adafruit_hashlib/_sha384.py
adafruit_hashlib/_sha512.py
adafruit_circuitpython_hashlib-1.4.20.dist-info/METADATA
adafruit_circuitpython_hashlib-1.4.20.dist-info/WHEEL
adafruit_circuitpython_hashlib-1.4.20.dist-info/top_level.txt
adafruit_circuitpython_hashlib-1.4.20.dist-info/RECORD
