Metadata-Version: 2.4
Name: adafruit-circuitpython-hashlib
Version: 1.4.20
Summary: Secure hashes and message digests
Author-email: Adafruit Industries <circuitpython@adafruit.com>
License: MIT
Project-URL: Homepage, https://github.com/adafruit/Adafruit_CircuitPython_hashlib
Keywords: adafruit,blinka,circuitpython,micropython,hashlib,hashes,,sha1,,sha224,,sha384,,sha512
Classifier: Intended Audience :: Developers
Classifier: Topic :: Software Development :: Libraries
Classifier: Topic :: Software Development :: Embedded Systems
Classifier: Topic :: System :: Hardware
Classifier: License :: OSI Approved :: MIT License
Classifier: Programming Language :: Python :: 3
License-File: LICENSE
Requires-Dist: Adafruit-Blinka
Provides-Extra: optional
Dynamic: license-file
